{"run_number": "1645288027013547", "step_name": "join_hists", "task_id": "57", "attempt_id": 0, "name": "_foreach_num_splits", "content_type": "gzip+pickle-v2", "type": "metaflow.artifact", "sha": "f3627f46179fdd95bf0e83101840fd1d71b60e40", "ds_type": "local", "location": ":root:/home/abd/Desktop/Work/Metaflow/BSM-Search/.metaflow", "flow_id": "BSM_Search", "user_name": "abd", "tags": [], "system_tags": ["user:abd", "date:2022-02-19", "runtime:dev", "python_version:3.8.10", "metaflow_version:2.5.0"], "ts_epoch": 1645288088803}